{
  "formatVersion": 1,
  "database": {
    "version": 8,
    "identityHash": "a38595252d5072670c66dc044b6bfdc1",
    "entities": [
      {
        "tableName": "BucketItem",
        "createSql": "CREATE TABLE IF NOT EXISTS `${TABLE_NAME}` (`itemName` TEXT NOT NULL, `itemDueDate` TEXT NOT NULL, `itemStatus` INTEGER NOT NULL, `itemCompletedDate` TEXT NOT NULL, `itemId` INTEGER PRIMARY KEY AUTOINCREMENT NOT NULL)",
        "fields": [
          {
            "fieldPath": "itemName",
            "columnName": "itemName",
            "affinity": "TEXT",
            "notNull": true
          },
          {
            "fieldPath": "itemDueDate",
            "columnName": "itemDueDate",
            "affinity": "TEXT",
            "notNull": true
          },
          {
            "fieldPath": "itemStatus",
            "columnName": "itemStatus",
            "affinity": "INTEGER",
            "notNull": true
          },
          {
            "fieldPath": "itemCompletedDate",
            "columnName": "itemCompletedDate",
            "affinity": "TEXT",
            "notNull": true
          },
          {
            "fieldPath": "itemId",
            "columnName": "itemId",
            "affinity": "INTEGER",
            "notNull": true
          }
        ],
        "primaryKey": {
          "columnNames": [
            "itemId"
          ],
          "autoGenerate": true
        },
        "indices": [],
        "foreignKeys": []
      }
    ],
    "views": [],
    "setupQueries": [
      "CREATE TABLE IF NOT EXISTS room_master_table (id INTEGER PRIMARY KEY,identity_hash TEXT)",
      "INSERT OR REPLACE INTO room_master_table (id,identity_hash) VALUES(42, 'a38595252d5072670c66dc044b6bfdc1')"
    ]
  }
}